<?xml version="1.0" encoding="utf-8"?>
<resources xmlns:android="http://schemas.android.com/apk/res/android">
<string name="app_banner_view_native_app_install_accessibility">"Google Play Store-ൽ നിന്ന് ആപ്പ് സ്വീകരിക്കുക: %s"</string>
<string name="app_banner_install">"ഇന്‍സ്റ്റാൾ ചെയ്യുക"</string>
<string name="menu_add_to_homescreen">"ഹോംസ്‌ക്രീനിൽ ചേർക്കുക"</string>
<string name="menu_add_to_homescreen_install">"ആപ്പ് ഇൻസ്‌റ്റാൾ ചെയ്യുക"</string>
<string name="added_to_homescreen">"%1$s എന്നയാളെ നിങ്ങളുടെ ഹോം സ്‌ക്രീനിൽ ചേർത്തു"</string>
<string name="pwa_install_bottom_sheet_accessibility">"ഈ ആപ്പ് ഇൻസ്‌റ്റാൾ ചെയ്യുക"</string>
<string name="pwa_install_bottom_sheet_screenshot">"സ്‌ക്രീൻഷോട്ട്"</string>
<string name="image_zoom_content_description">"സ്‌ക്രീൻഷോട്ട്. അടയ്ക്കാൻ ടാപ്പ് ചെയ്യുക."</string>
<string name="webapk_install_in_progress">"ഇപ്പോഴും മുമ്പത്തെ സൈറ്റ് ചേർത്തുകൊണ്ടിരിക്കുകയാണ്"</string>
<string name="webapk_install_failed">"ഇൻസ്റ്റാൾ ചെയ്യാനായില്ല"</string>
</resources>
