<?xml version="1.0" encoding="utf-8"?>
<resources xmlns:android="http://schemas.android.com/apk/res/android">
<string name="all_passwords_bottom_sheet_content_description">"Lista e kredencialeve për t\'u plotësuar me prekje."</string>
<string name="all_passwords_bottom_sheet_half_height">"Lista e kredencialeve për t\'u plotësuar me prekje është hapur në gjysmë lartësi."</string>
<string name="all_passwords_bottom_sheet_full_height">"Lista e kredencialeve për t\'u plotësuar me prekje është hapur në lartësi të plotë."</string>
<string name="all_passwords_bottom_sheet_closed">"Lista e kredencialeve për t\'u plotësuar me prekje është mbyllur."</string>
<string name="all_passwords_bottom_sheet_title">"Fjalëkalimet"</string>
<string name="all_passwords_bottom_sheet_title_gpm">"Zgjidh fjalëkalimin"</string>
<string name="all_passwords_bottom_sheet_search_hint">"Kërko"</string>
<string name="all_passwords_bottom_sheet_no_password">"Pa fjalëkalim"</string>
<string name="all_passwords_bottom_sheet_warning_dialog_message_first">"Nëse ke besim te %s, mund të përdorësh një fjalëkalim të ruajtur për një sajt tjetër."</string>
<string name="all_passwords_bottom_sheet_warning_dialog_message_second">"Provo të përdorësh një fjalëkalim unik për çdo sajt."</string>
<string name="all_passwords_bottom_sheet_subtitle">"Nëse ke besim te %s, mund të përdorësh një fjalëkalim të ruajtur për t\'u identifikuar"</string>
<string name="autofill_keyboard_accessory_content_description">"Fjalëkalimet që ofrohen"</string>
<string name="autofill_keyboard_accessory_modern_content_description">"Sugjerimet për plotësimin automatik ofrohen mbi tastierë"</string>
<string name="keyboard_accessory_sheet_hide">"Shfaq tastierën"</string>
<string name="iph_keyboard_accessory_fill_with_chrome">"Përdor sugjerimin për plotësimin automatik të Chrome"</string>
<string name="iph_keyboard_accessory_swipe_for_more">"Rrëshqit shpejt për të parë më shumë sugjerime"</string>
<string name="password_generation_accessory_button">"Sugjero fjalëkalim të fortë"</string>
<string name="password_generation_accessory_button_short">"Sugjero fjalëkalim"</string>
<string name="password_accessory_sheet_toggle">"Shfaq fjalëkalimet"</string>
<string name="password_accessory_sheet_opened">"Shfaqja e fjalëkalimeve të ruajtura dhe e opsioneve të fjalëkalimeve"</string>
<string name="address_accessory_sheet_title">"Adresat"</string>
<string name="address_accessory_sheet_toggle">"Shfaq adresat"</string>
<string name="address_accessory_sheet_opened">"Po shfaq adresat e ruajtura"</string>
<string name="credit_card_accessory_sheet_toggle">"Shfaq mënyrat e pagesës"</string>
<string name="credit_card_accessory_sheet_opened">"Po shfaq mënyrat e ruajtura të pagesës"</string>
<string name="iph_keyboard_accessory_payment_virtual_cards">"Përdor kartën tënde virtuale për më shumë siguri"</string>
</resources>
