<?xml version="1.0" encoding="utf-8"?>
<resources xmlns:android="http://schemas.android.com/apk/res/android">
<string name="prefs_site_settings">"Ustawienia witryn"</string>
<string name="all_sites">"Wszystkie witryny"</string>
<string name="ads_permission_title">"Reklamy"</string>
<string name="ar_permission_title">"Rzeczywistość rozszerzona"</string>
<string name="automatic_downloads_permission_title">"Pobieranie automatyczne"</string>
<string name="background_sync_permission_title">"Synchronizacja w tle"</string>
<string name="website_settings_bluetooth_scanning">"Skanowanie Bluetooth"</string>
<string name="website_settings_use_camera">"Kamera"</string>
<string name="clipboard_permission_title">"Schowek"</string>
<string name="website_settings_idle_detection">"Korzystanie z urządzenia"</string>
<string name="javascript_permission_title">"JavaScript"</string>
<string name="website_settings_device_location">"Lokalizacja"</string>
<string name="website_settings_federated_identity">"Logowanie się w przypadku innych firm"</string>
<string name="website_settings_use_mic">"Mikrofon"</string>
<string name="midi_sysex_permission_title">"Pełne sterowanie urządzeniami MIDI"</string>
<string name="motion_sensors_permission_title">"Czujniki ruchu"</string>
<string name="sensors_permission_title">"Czujniki ruchu lub światła"</string>
<string name="nfc_permission_title">"Urządzenia z funkcją NFC"</string>
<string name="push_notifications_permission_title">"Powiadomienia"</string>
<string name="popup_permission_title">"Pop-upy i przekierowania"</string>
<string name="protected_content">"Treść chroniona"</string>
<string name="sound_permission_title">"Dźwięk"</string>
<string name="vr_permission_title">"Rzeczywistość wirtualna"</string>
<string name="auto_dark_web_content_title">"Ciemny motyw witryn"</string>
<string name="desktop_site_title">"Wersja na komputer"</string>
<string name="website_settings_category_allowed">"Dopuszczone"</string>
<string name="website_settings_category_allowed_except_third_party">"Dozwolone, z wyjątkiem witryn innych firm"</string>
<string name="website_settings_category_allowed_recommended">"Dozwolone (zalecane)"</string>
<string name="website_settings_category_ask">"Najpierw zapytaj"</string>
<string name="website_settings_category_blocked">"Zablokowane"</string>
<string name="website_settings_category_notifications_quiet">"Pokazuj wiadomości dyskretnie (blokuje powiadomienia, by Ci nie przeszkadzały)"</string>
<string name="enable_notifications_vibrate_title">"Wibracje"</string>
<string name="enable_notifications_vibrate_summary">"Powiadomienia będą sygnalizowane wibracjami"</string>
<string name="enable_desktop_site_peripheral_title">"Accessories"</string>
<string name="enable_desktop_site_peripheral_summary">"Always request desktop site if a keyboard, trackpad, or mouse is attached"</string>
<string name="enable_desktop_site_external_display_title">"Displays"</string>
<string name="enable_desktop_site_external_display_summary">"Always request desktop site if a monitor is connected"</string>
<string name="website_settings_allowed_group_heading">"Dopuszczone"</string>
<string name="website_settings_blocked_group_heading">"Zablokowane"</string>
<string name="website_settings_exceptions_group_heading">"Wyjątki"</string>
<string name="website_settings_blocked_group_heading_sound">"Wyciszone"</string>
<string name="website_settings_allowed_group_heading_request_desktop_site">"Zawsze żądaj strony na komputery"</string>
<string name="website_settings_blocked_group_heading_request_desktop_site">"Zawsze żądaj strony mobilnej"</string>
<string name="website_settings_managed_group_heading">"Zarządzane przez aplikację"</string>
<string name="android_permission_off">"Przyznaj aplikacji %1$s uprawnienie w &lt;link&gt;ustawieniach Androida&lt;/link&gt;."</string>
<string name="android_permission_off_plural">"Przyznaj aplikacji %1$s uprawnienia w &lt;link&gt;ustawieniach Androida&lt;/link&gt;."</string>
<string name="website_settings_embedded_on">"Umieszczono na %1$s"</string>
<string name="clear_browsing_data_link">"Wyczyść dane przeglądania…"</string>
<string name="summary_with_one_bullet">"%1$s • %2$s"</string>
<string name="domain_settings_title">"Ustawienia domeny %1$s"</string>
<string name="website_settings_site_category">"Witryna"</string>
<string name="website_settings_usage_category">"Wykorzystanie"</string>
<string name="website_settings_permissions_category">"Uprawnienia"</string>
<string name="website_settings_permissions_description">"Zarządzaj dostępem tej strony do Twojego urządzenia"</string>
<string name="website_settings_permissions_allow">"Zezwalaj"</string>
<string name="website_settings_permissions_allowed_dse">"Zezwolono na dostęp obecnej wyszukiwarce"</string>
<string name="website_settings_permissions_block">"Blokuj"</string>
<string name="website_settings_permissions_blocked_dse">"Zablokowano dostęp obecnej wyszukiwarce"</string>
<string name="website_settings_third_party_cookies_exception_label">"Również pliki cookie innych firm na tej stronie"</string>
<string name="website_settings_add_site">"Dodaj witrynę do wyjątków"</string>
<string name="website_settings_add_site_dialog_title">"Dodaj stronę"</string>
<string name="website_settings_add_site_add_button">"Dodaj"</string>
<string name="website_settings_add_site_toast">"Strona %1$s została dodana"</string>
<string name="website_settings_add_site_site_url">"URL strony"</string>
<string name="example_url">"www.example.com"</string>
<string name="webstorage_clear_data_dialog_title">"Wyczyścić dane witryn?"</string>
<string name="webstorage_clear_data_dialog_ok_button">"Wyczyść"</string>
<string name="webstorage_clear_data_dialog_message_single">"Spowoduje to usunięcie wszystkich danych i plików cookie zapisanych przez stronę %1$s."</string>
<string name="webstorage_clear_data_dialog_message_single_with_app">"Spowoduje to usunięcie wszystkich danych i plików cookie zapisanych przez stronę %1$s lub jej aplikację na ekranie głównym."</string>
<string name="webstorage_clear_data_dialog_offline_message">"Wszystkie dane offline zostaną wyczyszczone."</string>
<string name="webstorage_clear_data_dialog_message">"Spowoduje to usunięcie %1$s danych i plików cookie zapisanych przez strony."</string>
<string name="webstorage_clear_data_dialog_message_with_app">"Spowoduje to usunięcie %1$s danych i plików cookie zapisanych przez stronę lub aplikacje na ekranie głównym."</string>
<string name="webstorage_clear_data_dialog_sign_out_message">"Wylogujemy Cię z tej strony."</string>
<string name="webstorage_clear_data_dialog_sign_out_all_message">"Wylogujemy Cię ze wszystkich stron."</string>
<string name="storage_clear_site_storage_title">"Wyczyścić dane witryn?"</string>
<string name="storage_clear_dialog_clear_storage_option">"Wyczyść"</string>
<string name="storage_clear_dialog_text">"Spowoduje to usunięcie %1$s danych witryn."</string>
<string name="website_reset">"Wyczyść i zresetuj"</string>
<string name="website_reset_full">"Wyczyść dane i zresetuj uprawnienia"</string>
<string name="website_reset_confirmation">"Na pewno chcesz usunąć wszystkie dane lokalne (w tym pliki cookie) i zresetować uprawnienia tej witryny?"</string>
<string name="chosen_object_website_reset_confirmation_for">"Czy na pewno chcesz zresetować wszystkie uprawnienia witryny dla obiektu %1$s?"</string>
<string name="intrusive_ads_information">"Na tej stronie wyświetlają się uciążliwe lub wprowadzające w błąd reklamy"</string>
<string name="website_settings_category_ads_blocked">"Blokuj reklamy na stronach, które wyświetlają reklamy uciążliwe lub wprowadzające w błąd"</string>
<string name="website_settings_category_ads_blocked_list">"Blokowane na niektórych stronach"</string>
<string name="website_settings_category_ar_ask">"Pytaj, zanim zezwolisz stronom na tworzenie mapy 3D Twojego otoczenia lub śledzenie pozycji kamery (zalecane)"</string>
<string name="website_settings_category_ar_blocked">"Nie zezwalaj stronom na tworzenie mapy 3D Twojego otoczenia ani na śledzenie pozycji kamery"</string>
<string name="android_ar_camera_permission_off">"Aby w aplikacji %1$s można było korzystać z rzeczywistości rozszerzonej, włącz też aparat w &lt;link&gt;ustawieniach Androida&lt;/link&gt;."</string>
<string name="website_settings_add_site_description_automatic_downloads">"Zezwól stronie na automatyczne pobieranie wielu plików."</string>
<string name="website_settings_add_site_description_background_sync">"Zezwalaj na synchronizowanie w tle z określoną stroną."</string>
<string name="website_settings_category_bluetooth_ask">"Pytaj, zanim zezwolisz stronom na połączenie z urządzeniem (zalecane)"</string>
<string name="website_settings_category_bluetooth_blocked">"Nie zezwalaj stronom na łączenie się z urządzeniami"</string>
<string name="website_settings_bluetooth">"Bluetooth"</string>
<string name="website_settings_category_bluetooth_scanning_ask">"Pytaj, gdy strona chce wykryć urządzenia Bluetooth w pobliżu (zalecane)"</string>
<string name="website_settings_category_camera_ask">"Pytaj, zanim zezwolisz stronom na korzystanie z aparatu (zalecane)"</string>
<string name="android_camera_permission_off">"Aby zezwolić aplikacji %1$s na dostęp do aparatu, musisz go też włączyć w &lt;link&gt;Ustawieniach Androida&lt;/link&gt;."</string>
<string name="website_settings_category_clipboard_ask">"Pytaj, czy zezwolić stronom na odczytywanie tekstu i obrazów ze schowka (zalecane)"</string>
<string name="website_settings_category_clipboard_blocked">"Zablokuj stronom możliwość odczytywania tekstu i obrazów ze schowka"</string>
<string name="website_settings_category_clipboard_blocked_list">"Zablokowano odczytywanie schowka"</string>
<string name="website_settings_category_cookie_allow_title">"Zezwalaj na pliki cookie"</string>
<string name="website_settings_category_cookie_block_third_party_incognito_title">"Blokuj pliki cookie innych firm w trybie incognito"</string>
<string name="website_settings_category_cookie_block_third_party_title">"Blokuj pliki cookie innych firm"</string>
<string name="website_settings_category_cookie_block_title">"Blokuj wszystkie pliki cookie (niezalecane)"</string>
<string name="website_settings_category_cookie_allow_addition">"Strony będą działać normalnie"</string>
<string name="website_settings_category_cookie_block_third_party_addition">"W niektórych witrynach mogą nie działać funkcje"</string>
<string name="website_settings_category_cookie_block_addition">"W wielu witrynach mogą nie działać funkcje"</string>
<string name="website_settings_category_cookie_allowed">"Zezwalaj witrynom na zapisywanie danych w plikach cookie i ich odczytywanie (zalecane)"</string>
<string name="website_settings_add_site_description_cookies_allow">"Zezwalaj na pliki cookie z określonej strony internetowej."</string>
<string name="website_settings_add_site_description_cookies_block">"Blokuj pliki cookie z określonej strony internetowej."</string>
<string name="website_settings_cookie_info">"Pliki cookie są tworzone przez odwiedzane witryny. Witryny zapisują w nich Twoje ustawienia. Pliki cookie innych firm są tworzone przez inne witryny. W tych witrynach znajdują się niektóre treści, np. reklamy i obrazy, które wyświetlają się na odwiedzanej stronie."</string>
<string name="website_settings_category_desktop_site_allowed">"Żądaj wersji na komputery"</string>
<string name="website_settings_category_desktop_site_blocked">"Żądaj wersji na urządzenia mobilne (zalecane)"</string>
<string name="website_settings_category_desktop_site_allowed_list">"Włączone"</string>
<string name="website_settings_category_desktop_site_blocked_list">"Wyłączone"</string>
<string name="website_settings_add_site_description_federated_identity_allow">"Zezwalanie na logowanie się innych firm w określonej witrynie."</string>
<string name="website_settings_add_site_description_federated_identity_block">"Blokowanie logowania się innych firm w określonej witrynie."</string>
<string name="website_settings_category_federated_identity_allowed">"Witryny mogą wyświetlać prośby o zalogowanie się pochodzące od usług tożsamości."</string>
<string name="website_settings_category_federated_identity_blocked">"Blokuj prośby o zalogowanie się pochodzące od usług tożsamości."</string>
<string name="website_settings_category_idle_detection_ask">"Pytaj, gdy strona chce wiedzieć, kiedy aktywnie korzystasz z urządzenia"</string>
<string name="website_settings_category_idle_detection_blocked">"Nie pozwalaj stronom sprawdzać, czy aktualnie używasz urządzenia"</string>
<string name="website_settings_category_javascript_allowed">"Zezwalaj na wykonywanie kodu JavaScript w witrynach (zalecane)"</string>
<string name="website_settings_add_site_description_javascript_allow">"Zezwól na użycie JavaScriptu w określonej witrynie."</string>
<string name="website_settings_add_site_description_javascript_block">"Zablokuj JavaScript w określonej witrynie."</string>
<string name="website_settings_category_location_ask">"Pytaj, zanim udostępnisz stronom swoją lokalizację (zalecane)"</string>
<string name="android_location_also_off_globally">"Dostęp do lokalizacji jest wyłączony też na tym urządzeniu. Włącz go w &lt;link&gt;Ustawieniach Androida&lt;/link&gt;."</string>
<string name="android_location_off_globally">"Dostęp do lokalizacji jest wyłączony na tym urządzeniu. Włącz go w &lt;link&gt;Ustawieniach Androida&lt;/link&gt;."</string>
<string name="android_location_permission_off">"Aby zezwolić aplikacji %1$s na dostęp do lokalizacji, musisz ją też włączyć w &lt;link&gt;ustawieniach Androida&lt;/link&gt;."</string>
<string name="website_location_settings">"Otwórz ustawienia lokalizacji"</string>
<string name="website_settings_category_mic_ask">"Pytaj, zanim zezwolisz stronom na korzystanie z mikrofonu (zalecane)"</string>
<string name="android_microphone_permission_off">"Aby zezwolić aplikacji %1$s na dostęp do mikrofonu, musisz go też włączyć w &lt;link&gt;ustawieniach Androida&lt;/link&gt;."</string>
<string name="website_settings_category_sensors_allowed">"Zezwalaj stronom na dostęp do czujników (zalecane)"</string>
<string name="website_settings_category_sensors_blocked">"Blokuj stronom dostęp do czujników"</string>
<string name="website_settings_category_motion_sensors_allowed">"Zezwalaj stronom na dostęp do czujników ruchu (zalecane)"</string>
<string name="website_settings_category_motion_sensors_blocked">"Blokuj stronom dostęp do czujników ruchu"</string>
<string name="website_settings_category_nfc_ask">"Pytaj, zanim zezwolisz stronom na odczytywanie i zmienianie informacji na urządzeniach z funkcją NFC (zalecane)"</string>
<string name="website_settings_category_nfc_blocked">"Nie zezwalaj stronom na odczytywanie i zmienianie informacji na urządzeniach z funkcją NFC"</string>
<string name="android_nfc_off_globally">"Funkcja NFC na tym urządzeniu jest wyłączona. Włącz ją w &lt;link&gt;Ustawieniach Androida&lt;/link&gt;."</string>
<string name="android_nfc_unsupported">"To urządzenie nie obsługuje NFC"</string>
<string name="website_settings_category_notifications_block">"Strony nie mogą prosić o zgodę na wysyłanie powiadomień"</string>
<string name="notifications_iph">"Zazwyczaj blokujesz powiadomienia. Aby na nie zezwolić, kliknij Szczegóły."</string>
<string name="website_settings_category_notifications_ask">"Strony mogą prosić o zgodę na wysyłanie powiadomień"</string>
<string name="website_setting_managed_by_app">"Zarządzane przez %1$s"</string>
<string name="android_notifications_permission_off">"Aby zezwolić aplikacji %1$s na wysyłanie do Ciebie powiadomień, musisz je też włączyć w &lt;link&gt;ustawieniach Androida&lt;/link&gt;."</string>
<string name="website_notification_settings">"Otwórz ustawienia powiadomień"</string>
<string name="website_settings_category_popups_redirects_blocked">"Blokuj wyskakujące okienka i przekierowania na stronach (zalecane)"</string>
<string name="website_settings_category_protected_content_allowed_recommended">"Zezwalaj stronom na odtwarzanie treści chronionej (zalecane)"</string>
<string name="website_settings_category_protected_content_allowed">"Zezwalaj stronom na odtwarzanie treści chronionych"</string>
<string name="website_settings_category_protected_content_ask_recommended">"Pytaj, zanim pozwolisz stronom na odtwarzanie treści chronionej (zalecane)"</string>
<string name="website_settings_category_protected_content_ask">"Pytaj, zanim zezwolisz stronom na odtwarzanie treści chronionej"</string>
<string name="website_settings_category_protected_content_blocked">"Blokuj odtwarzanie treści chronionej na stronach"</string>
<string name="website_settings_category_sound_allowed">"Zezwalaj na odtwarzanie dźwięku na stronach internetowych (zalecane)"</string>
<string name="website_settings_category_sound_blocked">"Wycisz strony, które odtwarzają dźwięk"</string>
<string name="website_settings_category_sound_blocked_list">"Wyciszone"</string>
<string name="website_settings_add_site_description_sound_allow">"Zezwalaj na dźwięk na określonej stronie."</string>
<string name="website_settings_add_site_description_sound_block">"Wycisz dźwięk na konkretnej stronie."</string>
<string name="website_settings_storage">"Zapisane dane"</string>
<string name="no_saved_website_settings">"W tym miejscu pojawiają się pliki zapisane przez witryny"</string>
<string name="origin_settings_storage_usage_brief">"%1$s zapisanych danych"</string>
<string name="storage_clear_button_title">"Wyczyść wszystkie dane"</string>
<string name="website_settings_category_usb_ask">"Pytaj, zanim zezwolisz stronom na połączenie z urządzeniem (zalecane)"</string>
<string name="website_settings_category_usb_blocked">"Nie zezwalaj stronom na łączenie się z urządzeniami"</string>
<string name="website_settings_revoke_all_permissions_for_device">"Anuluj wszystkie uprawnienia urządzenia"</string>
<string name="website_settings_revoke_device_permission">"Cofnij zgodę na dostęp do urządzenia"</string>
<string name="website_settings_usb">"USB"</string>
<string name="website_settings_category_vr_ask">"Pytaj, zanim zezwolisz stronom na korzystanie z urządzenia i danych rzeczywistości wirtualnej (zalecane)"</string>
<string name="website_settings_category_vr_blocked">"Nie zezwalaj stronom na korzystanie z urządzenia ani danych rzeczywistości wirtualnej"</string>
<string name="website_settings_category_auto_dark_allowed">"Stosuj ciemny motyw witryn w przypadkach, w których stosuje go Chrome, tam, gdzie to możliwe"</string>
<string name="website_settings_category_auto_dark_blocked">"Nie stosuj ciemnego motywu witryn"</string>
<string name="website_settings_add_site_description_auto_dark_block">"Nie stosuj ciemnego motywu konkretnej witryny"</string>
<string name="got_it">"Rozumiem"</string>
<string name="ok">"OK"</string>
<string name="ok_got_it">"Rozumiem"</string>
<string name="cancel">"Anuluj"</string>
<string name="save">"Zapisz"</string>
<string name="details_link">"Szczegóły"</string>
<string name="change_link">"Zmień"</string>
<string name="done">"Gotowe"</string>
<string name="delete">"Usuń"</string>
<string name="remove">"Usuń"</string>
<string name="reset">"Resetuj"</string>
<string name="title">"Tytuł"</string>
<string name="text_on">"Włączone"</string>
<string name="text_off">"Wyłączone"</string>
<string name="learn_more">"Dowiedz się więcej"</string>
<string name="more">"Więcej"</string>
<string name="close">"Zamknij"</string>
<string name="reload">"Odśwież"</string>
<string name="refresh">"Odśwież"</string>
<string name="no_thanks">"Nie, dziękuję"</string>
<string name="next">"Dalej"</string>
<string name="continue_button">"Dalej"</string>
<string name="submit">"Prześlij"</string>
<string name="undo">"Cofnij"</string>
<string name="help">"Pomoc"</string>
<string name="today">"Dzisiaj"</string>
<string name="yesterday">"Wczoraj"</string>
<string name="select">"Wybierz"</string>
<string name="add">"Dodaj"</string>
<string name="share">"Udostępnij"</string>
<string name="search">"Szukaj"</string>
<string name="settings">"Ustawienia"</string>
<string name="show_info">"Pokaż informacje"</string>
<string name="hide_info">"Ukryj informacje"</string>
<string name="copy_link">"Skopiuj link"</string>
<string name="copied">"Skopiowane"</string>
<string name="try_again">"Spróbuj ponownie"</string>
<string name="back">"Wstecz"</string>
<string name="confirm">"Potwierdź"</string>
<string name="show">"Pokaż"</string>
<string name="menu_item_move_up">"W górę"</string>
<string name="menu_item_move_down">"W dół"</string>
<string name="menu_item_move_to_top">"Przenieś na początek"</string>
<string name="just_once">"Tylko raz"</string>
<string name="dont_ask_again">"Nie pytaj ponownie"</string>
<string name="always">"Zawsze"</string>
<string name="latest">"Najnowsze"</string>
<string name="sort_by">"Sortuj według:"</string>
<string name="accessibility_toolbar_btn_menu">"Więcej opcji"</string>
<string name="accessibility_toolbar_btn_forward">"Dalej"</string>
<string name="accessibility_toolbar_btn_back">"Wróć"</string>
<string name="accessibility_toolbar_btn_delete_url">"Wyczyść wpisany tekst"</string>
<string name="accessibility_list_menu_button">"%1$s – opcje"</string>
<string name="accessibility_list_remove_button">"Usuń %1$s"</string>
<string name="accessibility_toolbar_screen_position">"Wybrano %1$s. Opcje dostępne na górze ekranu"</string>
<string name="accessibility_toolbar_multi_select">"Wybrano %1$s"</string>
<string name="accessibility_cancel_selection">"Anuluj wybór"</string>
<string name="accessibility_expand_button">"Rozwiń"</string>
<plurals name="selected_items">
  <item quantity="one">"Wybrano 1"</item>
  <item quantity="few">"Wybrano %d"</item>
  <item quantity="many">"Wybrano %d"</item>
  <item quantity="other">"Wybrano %d"</item>
</plurals>
<string name="select_items">"Wybierz elementy"</string>
<string name="accessibility_security_btn_secure">"Połączenie jest bezpieczne"</string>
<string name="accessibility_security_btn_warn">"Twoje połączenie z tą witryną nie jest bezpieczne"</string>
<string name="accessibility_security_btn_dangerous">"Ten pakiet jest niebezpieczny"</string>
<string name="concat_two_strings_with_periods">"%1$s. %2$s."</string>
<plurals name="cookie_controls_blocked_cookies">
  <item quantity="one">"Zablokowano 1 plik cookie"</item>
  <item quantity="few">"Zablokowano %d pliki cookie"</item>
  <item quantity="many">"Zablokowano %d plików cookie"</item>
  <item quantity="other">"Zablokowano %d pliku cookie"</item>
</plurals>
<string name="certtitle">"Przeglądarka certyfikatów"</string>
<string name="managed_by_your_organization">"O tym ustawieniu decyduje administrator."</string>
<string name="managed_by_your_parents">"Zarządzany przez Twoich rodziców"</string>
<string name="managed_by_your_parent">"Zarządzany przez Twojego rodzica"</string>
<string name="managed_settings_cannot_be_reset">"Ustawień zarządzanych nie można zresetować"</string>
<string name="accessibility_expanded_group">"Rozwinięty – kliknij, by zwinąć."</string>
<string name="accessibility_collapsed_group">"Zwinięty – kliknij, by rozwinąć."</string>
<string name="menu_help">"Pomoc i opinie"</string>
<string name="automatically_blocked">"Automatycznie zablokowane"</string>
<string name="download_notification_cancel_button">"Anuluj"</string>
<string name="download_notification_completed">"Pobieranie zakończone"</string>
<string name="download_notification_completed_with_size">"Ukończono pobieranie • %1$s"</string>
<string name="download_notification_failed">"Nie udało się pobrać"</string>
<string name="download_notification_paused">"Pobieranie wstrzymane"</string>
<string name="download_notification_pause_button">"Wstrzymaj"</string>
<string name="download_notification_resume_button">"Wznów"</string>
<string name="download_ui_determinate_bytes">"%1$s / %2$s"</string>
<string name="download_ui_indeterminate_bytes">"%1$s / ?"</string>
<string name="download_ui_kb">"%1$3.2f KB"</string>
<string name="download_ui_mb">"%1$3.2f MB"</string>
<string name="download_ui_gb">"%1$3.2f GB"</string>
<string name="blocked_navigation_warning">"Adres zablokowany: %1$s"</string>
<string name="unreachable_navigation_warning">"Adres nieosiągalny: %1$s"</string>
<string name="page_info_about_this_site_title">"Z sieci"</string>
<string name="page_info_about_this_page_title">"Informacje o tej stronie"</string>
<string name="page_info_about_this_page_description_placeholder">"Learn about its source and topic"</string>
<string name="page_info_about_this_site_subpage_from_label">"Źródło: %1$s"</string>
<string name="page_info_domain_hidden">"Treść z %1$s dostarczana przez Google."</string>
<string name="page_info_forget_site_title">"Zapomnieć tę stronę?"</string>
<string name="page_info_forget_site_message">"Czy na pewno chcesz zresetować uprawnienia oraz wyczyścić pliki cookie i dane witryn?"</string>
<string name="page_info_forget_site_confirmation_button">"Zapomnij"</string>
<string name="page_info_history_title">"Historia"</string>
<string name="page_info_history_forget">"Zapomnij tę stronę"</string>
<string name="page_info_history_last_visit_today">"Ostatnio używana dzisiaj"</string>
<string name="page_info_history_last_visit_yesterday">"Ostatnio używana wczoraj"</string>
<string name="page_info_history_last_visit_days">"Ostatnio używano %1$s dni temu"</string>
<string name="page_info_history_last_visit_date">"Ostatnia wizyta %1$s"</string>
<string name="page_info_permissions_title">"Uprawnienia"</string>
<string name="page_info_permissions_reset">"Zresetuj uprawnienia"</string>
<string name="page_info_permissions_reset_dialog_title">"Zresetować uprawnienia?"</string>
<string name="page_info_permissions_reset_confirmation">"Spowoduje to zresetowanie uprawnień witryny %1$s"</string>
<string name="page_info_permissions_os_warning">"%1$s – %2$s"</string>
<string name="page_info_permissions_summary_1_allowed">"Dozwolone: %1$s"</string>
<string name="page_info_permissions_summary_1_blocked">"Zablokowane: %1$s"</string>
<string name="page_info_permissions_summary_2_mixed">"Dozwolone: %1$s, zablokowane: %2$s"</string>
<string name="page_info_permissions_summary_2_allowed">"Dozwolone: %1$s i %2$s"</string>
<string name="page_info_permissions_summary_2_blocked">"Zablokowane: %1$s i %2$s"</string>
<plurals name="page_info_permissions_summary_more_mixed">
  <item quantity="one">"%1$s, %2$s i jeszcze %3$s"</item>
  <item quantity="few">"%1$s, %2$s i jeszcze %3$s"</item>
  <item quantity="many">"%1$s, %2$s i jeszcze %3$s"</item>
  <item quantity="other">"%1$s, %2$s i jeszcze %3$s"</item>
</plurals>
<plurals name="page_info_permissions_summary_more_allowed">
  <item quantity="one">"Dozwolone: %1$s, %2$s i jeszcze %3$s"</item>
  <item quantity="few">"Dozwolone: %1$s, %2$s i jeszcze %3$s"</item>
  <item quantity="many">"Dozwolone: %1$s, %2$s i jeszcze %3$s"</item>
  <item quantity="other">"Dozwolone: %1$s, %2$s i jeszcze %3$s"</item>
</plurals>
<plurals name="page_info_permissions_summary_more_blocked">
  <item quantity="one">"Zablokowane: %1$s, %2$s i jeszcze %3$s"</item>
  <item quantity="few">"Zablokowane: %1$s, %2$s i jeszcze %3$s"</item>
  <item quantity="many">"Zablokowane: %1$s, %2$s i jeszcze %3$s"</item>
  <item quantity="other">"Zablokowane: %1$s, %2$s i jeszcze %3$s"</item>
</plurals>
<string name="page_info_instant_app_button">"Otwórz aplikację błyskawiczną"</string>
<string name="page_info_lite_mode_https_image_compression">"Aby zaoszczędzić dane, obrazy z tej strony zostały zoptymalizowane przez Google."</string>
<string name="page_info_open_online_button">"Otwórz online"</string>
<string name="page_info_site_settings_button">"Ustawienia witryn"</string>
<string name="page_info_cookies_clear">"Usunąć pliki cookie?"</string>
<string name="page_info_cookies_clear_confirmation">"Spowoduje to usunięcie plików cookie witryny %1$s"</string>
<string name="page_info_cookies_clear_confirmation_button">"Wyczyść"</string>
<string name="page_info_cookies_description">"Plików cookie i innych danych stron używamy, żeby Cię zapamiętać, na przykład w celu logowania czy personalizowania reklam. Plikami cookie wszystkich stron możesz zarządzać w &lt;link&gt;Ustawieniach&lt;/link&gt;."</string>
<string name="page_info_cookies_block">"Blokuj pliki cookie innych firm"</string>
<plurals name="page_info_cookies_in_use">
  <item quantity="one">"1 plik cookie w użyciu"</item>
  <item quantity="few">"%d pliki cookie w użyciu"</item>
  <item quantity="many">"%d plików cookie w użyciu"</item>
  <item quantity="other">"%d pliku cookie w użyciu"</item>
</plurals>
<string name="page_info_android_location_blocked">"Wyłączona na tym urządzeniu"</string>
<string name="page_info_android_nfc_unsupported">"To urządzenie nie obsługuje NFC"</string>
<string name="page_info_android_permission_blocked">"Wyłączone w ustawieniach Androida"</string>
<string name="page_info_android_ar_camera_blocked">"Kamera jest wyłączona w ustawieniach Androida"</string>
<string name="page_info_url_expanded">"URL pokazany w całości"</string>
<string name="page_info_url_truncated">"URL obcięty"</string>
<string name="page_info_ad_personalization_title">"Personalizacja reklam"</string>
<string name="page_info_ad_personalization_topics_and_interest_group_description">"Ta witryna określa zainteresowania, których inne witryny mogą używać, aby wyświetlać Ci reklamy. Witryna wykorzystuje też gromadzone przez Chrome informacje o Twoich zainteresowaniach, aby wyświetlać trafniejsze reklamy."</string>
<string name="page_info_ad_personalization_topics_description">"Witryna korzysta z gromadzonych przez Chrome informacji o Twoich zainteresowaniach, aby wyświetlać trafniejsze reklamy"</string>
<string name="page_info_ad_personalization_interest_group_description">"Ta witryna określa zainteresowania, których inne witryny mogą używać, aby wyświetlać Ci reklamy"</string>
<string name="page_info_ad_manage_interests">"Zarządzaj zainteresowaniami"</string>
<string name="cookies_title">"Pliki cookie"</string>
<string name="accessibility_toolbar_btn_site_info">"Informacje o witrynie"</string>
<string name="accessibility_toolbar_view_site_info">"Wyświetl informacje o witrynie"</string>
<string name="media_capture_notification_app_name_separator">"%1$s–%2$s"</string>
<string name="video_capture_notification_title">"Strona używa kamery"</string>
<string name="audio_capture_notification_title">"Strona używa mikrofonu"</string>
<string name="video_audio_capture_notification_title">"Strona używa kamery i mikrofonu"</string>
<string name="media_capture_notification_content_text">"Kliknij, by wrócić na %1$s"</string>
<string name="media_capture_notification_content_text_incognito">"Kliknij, by wrócić na tę stronę"</string>
<string name="accessibility_stop">"Zatrzymaj"</string>
<string name="notification_incognito_tab">"Karta incognito"</string>
<string name="notification_category_completed_downloads">"Ukończenie pobierania plików"</string>
<string name="notification_category_downloads">"W trakcie pobierania"</string>
<string name="notification_category_media_playback">"Odtwarzanie multimediów"</string>
<string name="notification_category_webrtc_cam_and_mic">"Korzystanie z kamery i mikrofonu"</string>
<string name="screen_capture_notification_title">"Udostępnianie ekranu"</string>
<string name="connected_to_bluetooth_device_notification_title">"Połączono z urządzeniem Bluetooth"</string>
<string name="scanning_for_bluetooth_devices_notification_title">"Skanuję w poszukiwaniu urządzeń Bluetooth"</string>
<string name="bluetooth_notification_content_text">"Kliknij, by wrócić na %1$s"</string>
<string name="bluetooth_notification_content_text_incognito">"Kliknij, by wrócić na tę stronę"</string>
<string name="connected_to_usb_device_notification_title">"Połączona z urządzeniem USB"</string>
<string name="usb_notification_content_text">"Kliknij, by wrócić na %1$s"</string>
<string name="usb_notification_content_text_incognito">"Kliknij, by wrócić na tę stronę"</string>
<string name="share_link_chooser_title">"Udostępnij przez"</string>
<string name="accessibility_play">"Odtwórz"</string>
<string name="accessibility_pause">"Wstrzymaj"</string>
<string name="accessibility_replay">"Odtwórz od początku"</string>
<string name="accessibility_previous_track">"Poprzedni utwór"</string>
<string name="accessibility_next_track">"Następny utwór"</string>
<string name="accessibility_seek_forward">"Przewiń do przodu"</string>
<string name="accessibility_seek_backward">"Przewiń do tyłu"</string>
<string name="accessibility_hang_up">"Rozłącz"</string>
<string name="accessibility_mute_microphone">"Wycisz mikrofon"</string>
<string name="accessibility_unmute_microphone">"Włącz mikrofon"</string>
<string name="accessibility_turn_on_camera">"Włącz kamerę"</string>
<string name="accessibility_turn_off_camera">"Wyłącz kamerę"</string>
<string name="media_notification_incognito">"Strona odtwarza multimedia"</string>
<string name="bottom_sheet_accessibility_description">"Przesuń w dół, by zamknąć."</string>
<string name="client_cert_unsupported_title">"Nie można wybrać certyfikatu."</string>
<string name="client_cert_unsupported_message">"Wybieranie certyfikatu klienta nie jest obsługiwane przez ten system operacyjny."</string>
<string name="bottom_bar_screen_position">"Opcje dostępne u dołu ekranu"</string>
<string name="external_app_leave_incognito_warning">"Ta strona zamierza udostępnić informacje aplikacji poza trybem incognito."</string>
<string name="external_app_leave_incognito_warning_title">"Wyłączyć tryb incognito?"</string>
<string name="external_app_leave_incognito_stay">"Zostań"</string>
<string name="external_app_leave_incognito_leave">"Wyjdź"</string>
<string name="contacts_picker_search">"Wyszukaj w kontaktach"</string>
<string name="contacts_picker_select_contacts">"Wybierz kontakty"</string>
<string name="contacts_picker_select_contact">"Wybierz kontakt"</string>
<string name="contacts_picker_all_contacts">"Wszystkie kontakty"</string>
<string name="contacts_picker_no_contacts_found">"Nie znaleziono kontaktów"</string>
<string name="top_view_names_filter_label">"Nazwy"</string>
<string name="top_view_address_filter_label">"Adresy"</string>
<string name="top_view_email_filter_label">"Adresy e-mail"</string>
<string name="top_view_telephone_filter_label">"Numery telefonów"</string>
<string name="top_view_icon_filter_label">"Zdjęcia profilowe"</string>
<plurals name="contacts_picker_more_details">
  <item quantity="one">"(i jeszcze 1)"</item>
  <item quantity="few">"(i jeszcze %d)"</item>
  <item quantity="many">"(i jeszcze %d)"</item>
  <item quantity="other">"(i jeszcze %d)"</item>
</plurals>
<string name="disclaimer_sharing_contact_details">"Wybrane kontakty zostaną udostępnione witrynie &lt;b&gt;%1$s&lt;/b&gt;."</string>
<string name="photo_picker_select_images">"Wybierz zdjęcia"</string>
<string name="photo_picker_select_image">"Wybierz obraz"</string>
<string name="photo_picker_camera">"Kamera"</string>
<string name="photo_picker_browse">"Przeglądaj"</string>
<string name="photo_picker_video_duration">"%1$s/%2$s"</string>
<string name="photo_picker_accessibility_zoom_in">"Powiększ"</string>
<string name="photo_picker_accessibility_zoom_out">"Pomniejsz"</string>
<string name="decoder_description">"Dekoder obrazów"</string>
<string name="fast_forward_hint">"Kliknij dwukrotnie z lewej lub prawej strony filmu, by przewinąć o 10 s"</string>
<string name="accessibility_play_video">"Odtwórz film"</string>
<string name="accessibility_pause_video">"Wstrzymaj film"</string>
<string name="accessibility_mute_video">"Wycisz film"</string>
<string name="accessibility_unmute_video">"Wyłącz wyciszenie filmu"</string>
<string name="accessibility_full_screen">"Pełny ekran"</string>
<string name="accessibility_exit_full_screen">"Zamknij pełny ekran"</string>
<string name="accessibility_ntp_offline_badge">"Dostępny offline"</string>
<string name="accessibility_video_player">"Odtwarzacz"</string>
<string name="accessibility_playback_time">"Upłynęło: %1$s z %2$s"</string>
<string name="immersive_fullscreen_api_notification">"Przeciągnij od góry i kliknij przycisk Wstecz, by wyjść z trybu pełnoekranowego."</string>
<string name="webapk_report_abuse_dialog_title">"Odinstalować aplikację „%1$s”?"</string>
<string name="webapk_report_abuse_checkbox">"Zgłoś nadużycie"</string>
<string name="webapk_report_abuse_confirm">"Odinstaluj"</string>
<string name="webapk_report_abuse_cancel">"Anuluj"</string>
<string name="message_screen_position">"Opcja dostępna u góry ekranu"</string>
<string name="iph_snooze">"Przypomnij mi"</string>
<string name="chip_remove_icon_content_description">"Usuń: „%1$s”"</string>
<string name="prefs_accessibility">"Ułatwienia dostępu"</string>
<string name="font_size">"Skalowanie tekstu"</string>
<string name="font_size_preview_text">"Przeciągaj suwak, by umożliwić wygodne czytanie. Gdy dwukrotnie klikniesz akapit, tekst powiększy się co najmniej do tej wielkości."</string>
<string name="force_enable_zoom_title">"Wymuś powiększenie"</string>
<string name="force_enable_zoom_summary">"Zignoruj żądanie strony, gdy chce zapobiec powiększeniu widoku"</string>
<string name="reader_for_accessibility_title">"Uproszczony widok stron internetowych"</string>
<string name="reader_for_accessibility_summary">"Otrzymuj powiadomienia, gdy artykuł można wyświetlić w widoku uproszczonym"</string>
<string name="accessibility_tab_switcher_title">"Uproszczony widok otwartych kart"</string>
<string name="accessibility_tab_switcher_summary">"Zalecane, gdy włączono TalkBack lub Switch Access"</string>
<string name="accessibility_captions_title">"Napisy"</string>
<string name="page_zoom_title">"Zoom"</string>
<string name="page_zoom_summary">"Make the default text and images on sites smaller or larger"</string>
<string name="page_zoom_decrease_zoom_button_text">"Decrease zoom"</string>
<string name="page_zoom_increase_zoom_button_text">"Increase zoom"</string>
<string name="page_zoom_factor">"%1$d %%"</string>
<string name="page_zoom_always_show_preference_title">"Show zoom"</string>
<string name="page_zoom_always_show_preference_summary">"Zoom in or out on a page from the main menu"</string>
<string name="page_zoom_preview_title">"Preview"</string>
<string name="page_zoom_preview_text_title">"The Wonderful Wizard of Oz"</string>
<string name="page_zoom_preview_text_summary">"Chapter 11: The Wonderful Emerald City of Oz"</string>
<string name="page_zoom_preview_text_item">"Even with eyes protected by the green spectacles Dorothy and her friends were at first dazzled by the"</string>
<string name="search_resumption_module_title">"Sugerowane wyszukiwania na podstawie ostatnio otwartej karty"</string>
<string name="search_resumption_module_title_short">"Sugerowane wyszukiwania"</string>
<string name="search_resumption_module_subtitle">"Na podstawie ostatniej karty"</string>
<string name="accessibility_expanded">"Rozwinięty"</string>
<string name="accessibility_collapsed">"Zwinięty"</string>
</resources>
